{"dependencies":[{"name":"/root/nos-client-new/my-smartT-dapp/package.json","includedInParent":true,"mtime":1530770845430},{"name":"/root/nos-client-new/my-smartT-dapp/node_modules/core-js/package.json","includedInParent":true,"mtime":1522166898000},{"name":"./_global","loc":{"line":1,"column":21}}],"generated":{"js":"\nvar e=require(\"./_global\"),r=e.navigator;module.exports=r&&r.userAgent||\"\";","map":{"mappings":[{"source":"../node_modules/core-js/modules/_user-agent.js","original":{"line":1,"column":0},"generated":{"line":3,"column":0}},{"source":"../node_modules/core-js/modules/_user-agent.js","original":{"line":2,"column":0},"generated":{"line":4,"column":0}},{"source":"../node_modules/core-js/modules/_user-agent.js","original":{"line":3,"column":0},"generated":{"line":5,"column":0}},{"source":"../node_modules/core-js/modules/_user-agent.js","original":{"line":4,"column":0},"generated":{"line":6,"column":0}},{"source":"../node_modules/core-js/modules/_user-agent.js","original":{"line":5,"column":0},"generated":{"line":7,"column":0}}],"sources":{"../node_modules/core-js/modules/_user-agent.js":"var global = require('./_global');\nvar navigator = global.navigator;\n\nmodule.exports = navigator && navigator.userAgent || '';\n"},"lineCount":7}},"hash":"e87bb557b77e75d4d803c6d0cb4832a3","cacheData":{"env":{}}}