{"dependencies":[{"name":"/root/nos-client-new/latest-smartt-code/package.json","includedInParent":true,"mtime":1532420826470},{"name":"/root/nos-client-new/latest-smartt-code/node_modules/css-vendor/package.json","includedInParent":true,"mtime":499162500000},{"name":"./camelize","loc":{"line":8,"column":24}}],"generated":{"js":"\"use strict\";Object.defineProperty(exports,\"__esModule\",{value:!0}),exports.default=u;var e=require(\"./camelize\"),t=r(e);function r(e){return e&&e.__esModule?e:{default:e}}function u(e){return(0,t.default)(\"-\"+e)}","map":{"mappings":[{"source":"../node_modules/css-vendor/lib/utils/pascalize.js","original":{"line":1,"column":0},"generated":{"line":1,"column":0}},{"source":"../node_modules/css-vendor/lib/utils/pascalize.js","original":{"line":2,"column":0},"generated":{"line":2,"column":0}},{"source":"../node_modules/css-vendor/lib/utils/pascalize.js","original":{"line":3,"column":0},"generated":{"line":3,"column":0}},{"source":"../node_modules/css-vendor/lib/utils/pascalize.js","original":{"line":4,"column":0},"generated":{"line":4,"column":0}},{"source":"../node_modules/css-vendor/lib/utils/pascalize.js","original":{"line":5,"column":0},"generated":{"line":5,"column":0}},{"source":"../node_modules/css-vendor/lib/utils/pascalize.js","original":{"line":6,"column":0},"generated":{"line":6,"column":0}},{"source":"../node_modules/css-vendor/lib/utils/pascalize.js","original":{"line":7,"column":0},"generated":{"line":7,"column":0}},{"source":"../node_modules/css-vendor/lib/utils/pascalize.js","original":{"line":8,"column":0},"generated":{"line":8,"column":0}},{"source":"../node_modules/css-vendor/lib/utils/pascalize.js","original":{"line":9,"column":0},"generated":{"line":9,"column":0}},{"source":"../node_modules/css-vendor/lib/utils/pascalize.js","original":{"line":10,"column":0},"generated":{"line":10,"column":0}},{"source":"../node_modules/css-vendor/lib/utils/pascalize.js","original":{"line":11,"column":0},"generated":{"line":11,"column":0}},{"source":"../node_modules/css-vendor/lib/utils/pascalize.js","original":{"line":12,"column":0},"generated":{"line":12,"column":0}},{"source":"../node_modules/css-vendor/lib/utils/pascalize.js","original":{"line":13,"column":0},"generated":{"line":13,"column":0}},{"source":"../node_modules/css-vendor/lib/utils/pascalize.js","original":{"line":14,"column":0},"generated":{"line":14,"column":0}},{"source":"../node_modules/css-vendor/lib/utils/pascalize.js","original":{"line":15,"column":0},"generated":{"line":15,"column":0}},{"source":"../node_modules/css-vendor/lib/utils/pascalize.js","original":{"line":16,"column":0},"generated":{"line":16,"column":0}},{"source":"../node_modules/css-vendor/lib/utils/pascalize.js","original":{"line":17,"column":0},"generated":{"line":17,"column":0}},{"source":"../node_modules/css-vendor/lib/utils/pascalize.js","original":{"line":18,"column":0},"generated":{"line":18,"column":0}},{"source":"../node_modules/css-vendor/lib/utils/pascalize.js","original":{"line":19,"column":0},"generated":{"line":19,"column":0}},{"source":"../node_modules/css-vendor/lib/utils/pascalize.js","original":{"line":20,"column":0},"generated":{"line":20,"column":0}},{"source":"../node_modules/css-vendor/lib/utils/pascalize.js","original":{"line":21,"column":0},"generated":{"line":21,"column":0}},{"source":"../node_modules/css-vendor/lib/utils/pascalize.js","original":{"line":22,"column":0},"generated":{"line":22,"column":0}},{"source":"../node_modules/css-vendor/lib/utils/pascalize.js","original":{"line":23,"column":0},"generated":{"line":23,"column":0}}],"sources":{"../node_modules/css-vendor/lib/utils/pascalize.js":"'use strict';\n\nObject.defineProperty(exports, \"__esModule\", {\n  value: true\n});\nexports['default'] = pascalize;\n\nvar _camelize = require('./camelize');\n\nvar _camelize2 = _interopRequireDefault(_camelize);\n\nfunction _interopRequireDefault(obj) { return obj && obj.__esModule ? obj : { 'default': obj }; }\n\n/**\n * Convert dash separated strings to pascal cased.\n *\n * @param {String} str\n * @return {String}\n * @api private\n */\nfunction pascalize(str) {\n  return (0, _camelize2['default'])('-' + str);\n}"},"lineCount":23}},"hash":"4fb2ce84d355b70c730210803b22505e","cacheData":{"env":{}}}